gpflowopt/__init__.py
gpflowopt/_version.py
gpflowopt/bo.py
gpflowopt/design.py
gpflowopt/domain.py
gpflowopt/models.py
gpflowopt/objective.py
gpflowopt/optim.py
gpflowopt/pareto.py
gpflowopt/scaling.py
gpflowopt/transforms.py
gpflowopt/acquisition/__init__.py
gpflowopt/acquisition/acquisition.py
gpflowopt/acquisition/ei.py
gpflowopt/acquisition/hvpoi.py
gpflowopt/acquisition/lcb.py
gpflowopt/acquisition/mes.py
gpflowopt/acquisition/pof.py
gpflowopt/acquisition/poi.py
gpflowopt_master-0.1.1.dist-info/LICENSE
gpflowopt_master-0.1.1.dist-info/METADATA
gpflowopt_master-0.1.1.dist-info/WHEEL
gpflowopt_master-0.1.1.dist-info/top_level.txt
gpflowopt_master-0.1.1.dist-info/RECORD
